random_compliments/__init__.py
random_compliments/__main__.py
random_compliments/auto_start.py
random_compliments/cli.py
random_compliments/compliment_daemon.py
random_compliments/compliments.py
random_compliments/daemon_cli.py
random_compliments/install_hooks.py
random_compliments/notification_cli.py
random_compliments/post_install.py
random_compliments/wrapper.py
random_compliments-0.7.0.dist-info/licenses/LICENSE
random_compliments-0.7.0.dist-info/METADATA
random_compliments-0.7.0.dist-info/WHEEL
random_compliments-0.7.0.dist-info/entry_points.txt
random_compliments-0.7.0.dist-info/top_level.txt
random_compliments-0.7.0.dist-info/RECORD
