Metadata-Version: 2.4
Name: random-compliments
Version: 0.7.0
Summary: A package that delivers compliments about Boaz, the most interesting man in the world
Home-page: https://github.com/yourusername/random-compliments
Author: Boaz
Author-email: probably.wont.read.this@example.com
Classifier: Programming Language :: Python :: 3
Classifier: License :: OSI Approved :: MIT License
Classifier: Operating System :: OS Independent
Classifier: Topic :: Software Development :: Libraries :: Python Modules
Classifier: Intended Audience :: Developers
Requires-Python: >=3.6
License-File: LICENSE
Dynamic: author
Dynamic: author-email
Dynamic: classifier
Dynamic: description
Dynamic: description-content-type
Dynamic: home-page
Dynamic: license-file
Dynamic: requires-python
Dynamic: summary
